marops_cli/__init__.py
marops_cli/banner.py
marops_cli/cli.py
marops_cli/helpers.py
marops_cli/docker/docker-compose.base.yaml
marops_cli/docker/docker-compose.demo.yaml
marops_cli/docker/docker-compose.dev.yaml
marops_cli/docker/docker-compose.prod.yaml
marops_cli/groups/__init__.py
marops_cli/groups/base.py
marops_cli/groups/poetry.py
marops_cli/groups/setup.py
marops_cli-3.9.0.dist-info/METADATA
marops_cli-3.9.0.dist-info/WHEEL
marops_cli-3.9.0.dist-info/entry_points.txt
marops_cli-3.9.0.dist-info/top_level.txt
marops_cli-3.9.0.dist-info/zip-safe
marops_cli-3.9.0.dist-info/RECORD
